umleitung/__init__.py
umleitung/mcp_config_ext.py
umleitung/proxy.py
umleitung-0.2.0.dist-info/LICENSE
umleitung-0.2.0.dist-info/METADATA
umleitung-0.2.0.dist-info/WHEEL
umleitung-0.2.0.dist-info/RECORD
