Metadata-Version: 2.3
Name: umleitung
Version: 0.2.0
Summary: 
License: MIT
Author: Ilja Bauer
Author-email: iljabauer@gmail.com
Requires-Python: >=3.11,<4.0
Classifier: License :: OSI Approved :: MIT License
Classifier: Programming Language :: Python :: 3
Classifier: Programming Language :: Python :: 3.11
Classifier: Programming Language :: Python :: 3.12
Classifier: Programming Language :: Python :: 3.13
Requires-Dist: fastmcp (>=2.10.5,<3.0.0)
